mkdocs_freetext/__init__.py
mkdocs_freetext/plugin.py
mkdocs_freetext-1.0.0.dist-info/licenses/LICENSE
tests/__init__.py
tests/test_plugin.py
mkdocs_freetext-1.0.0.dist-info/METADATA
mkdocs_freetext-1.0.0.dist-info/WHEEL
mkdocs_freetext-1.0.0.dist-info/entry_points.txt
mkdocs_freetext-1.0.0.dist-info/top_level.txt
mkdocs_freetext-1.0.0.dist-info/RECORD
