Metadata-Version: 2.4
Name: mkdocs-freetext
Version: 1.0.0
Summary: A comprehensive MkDocs plugin for adding interactive free-text questions and assessments
Home-page: https://github.com/your-username/mkdocs-freetext
Author: Your Name
Author-email: Drew Kearsey <drew.kearsey@kubrickgroup.com>
Maintainer-email: Drew Kearsey <drew.kearsey@kubrickgroup.com>
License: MIT
Project-URL: Homepage, https://github.com/yourusername/mkdocs-freetext
Project-URL: Documentation, https://github.com/yourusername/mkdocs-freetext
Project-URL: Repository, https://github.com/yourusername/mkdocs-freetext
Project-URL: Bug Tracker, https://github.com/yourusername/mkdocs-freetext/issues
Keywords: mkdocs,plugin,freetext,questions,assessment,education,material,interactive,learning
Classifier: Development Status :: 5 - Production/Stable
Classifier: Intended Audience :: Education
Classifier: Intended Audience :: Developers
Classifier: License :: OSI Approved :: MIT License
Classifier: Operating System :: OS Independent
Classifier: Programming Language :: Python :: 3
Classifier: Programming Language :: Python :: 3.8
Classifier: Programming Language :: Python :: 3.9
Classifier: Programming Language :: Python :: 3.10
Classifier: Programming Language :: Python :: 3.11
Classifier: Programming Language :: Python :: 3.12
Classifier: Topic :: Documentation
Classifier: Topic :: Education
Classifier: Topic :: Text Processing :: Markup :: Markdown
Classifier: Framework :: MkDocs
Requires-Python: >=3.7
License-File: LICENSE
Requires-Dist: mkdocs>=1.4.0
Requires-Dist: markdown>=3.3.0
Dynamic: author
Dynamic: home-page
Dynamic: license-file
Dynamic: requires-python
